Neuro_fuzzy_EVAMortus/__init__.py
Neuro_fuzzy_EVAMortus/main.py
Neuro_fuzzy_EVAMortus-0.0.2.dist-info/LICENSE
Neuro_fuzzy_EVAMortus-0.0.2.dist-info/METADATA
Neuro_fuzzy_EVAMortus-0.0.2.dist-info/WHEEL
Neuro_fuzzy_EVAMortus-0.0.2.dist-info/top_level.txt
Neuro_fuzzy_EVAMortus-0.0.2.dist-info/RECORD
