Metadata-Version: 2.1
Name: Neuro-fuzzy-EVAMortus
Version: 0.0.2
Summary: Fuzzy output module
Home-page: 
Author: Ermakov Vitaliy
Author-email: blackcheshireshusband@yandex.ru
Classifier: Programming Language :: Python :: 3.10
Classifier: License :: OSI Approved :: MIT License
Classifier: Operating System :: OS Independent
Requires-Python: >=3.10
License-File: LICENSE
